{
  "id": 1762337544484,
  "title": "My Art Journey",
  "script": "Anushka: Namaste doston! Aaj main aap sabse apni kala yatra ke baare mein baat karna chahti hoon.\nAnushka: Ye sab shuru hua bachpan mein, rangon se khelte hue. Tab pata nahi tha ki ye mera passion ban jaayega.\nAnushka: School mein drawing competitions mein hissa leti thi. Jeeti bhi, haari bhi, lekin seekhti rahi.\nAnushka: Phir college mein fine arts join kiya. Wahan pata chala, kala sirf painting nahi, ek duniya hai.\nAnushka: Kai tarah ke mediums try kiye - oil paints, watercolors, even sculpting. Har cheez mein kuch naya mila.\nAnushka: Lekin sach kahun toh, raasta aasaan nahi tha. Kai baar laga, shayad main sahi nahi hoon.\nAnushka: Par jab bhi aisa laga, maine firse shuru kiya. Apne dil ki suni.\nAnushka: Ab main ek artist hoon. Paintings banati hoon. Logon ko apni kala se khushi deti hoon.\nAnushka: Aur yeh sab, sirf rangon se shuru hua tha! Dhanyavaad!",
  "config": {
    "language": "Hindi",
    "length": "short",
    "type": "face",
    "hostName": "Anushka",
    "participantName": "Anushka",
    "gender": "female",
    "topic": "My Art Journey",
    "customQuestions": [],
    "autoGenerated": true
  },
  "duration": "1:00",
  "createdAt": "2025-11-05T10:12:23.795Z",
  "language": "Hindi",
  "hostName": "Anushka"
}